<?xml version="1.0" ?>
<Imageset Name="CharHeadFrame4" Imagefile="Icons/CharHeadFrame4.tga" AutoScaled="true">

  <Image Name="CharHeadFrame4_ZBS201901_Player" XPos="0" YPos="0" Width="64" Height="64" />

  <Image Name="CharHeadFrame4_ZBS201901_Target" XPos="64" YPos="0" Width="64" Height="64" />

  <Image Name="CharHeadFrame4_ZBS201902_Player" XPos="128" YPos="0" Width="64" Height="64" />

  <Image Name="CharHeadFrame4_ZBS201902_Target" XPos="192" YPos="0" Width="64" Height="64" />

  <Image Name="CharHeadFrame4_ZBS201903_Player" XPos="0" YPos="64" Width="64" Height="64" />

  <Image Name="CharHeadFrame4_ZBS201903_Target" XPos="64" YPos="64" Width="64" Height="64" />

  <Image Name="CharHeadFrame4_ZBS201904_Player" XPos="128" YPos="64" Width="64" Height="64" />

  <Image Name="CharHeadFrame4_ZBS201904_Target" XPos="192" YPos="64" Width="64" Height="64" />

  <Image Name="CharHeadFrame4_ZBS201905_Player" XPos="0" YPos="128" Width="64" Height="64" />

  <Image Name="CharHeadFrame4_ZBS201905_Target" XPos="64" YPos="128" Width="64" Height="64" />

  <Image Name="CharHeadFrame4_ZBS201906_Player" XPos="128" YPos="128" Width="64" Height="64" />

  <Image Name="CharHeadFrame4_ZBS201906_Target" XPos="192" YPos="128" Width="64" Height="64" />

  

  <Image Name="CharHeadFrame4_DFS201901_Player" XPos="0" YPos="192" Width="64" Height="64" />

  <Image Name="CharHeadFrame4_DFS201901_Target" XPos="64" YPos="192" Width="64" Height="64" />

  <Image Name="CharHeadFrame4_DFS201902_Player" XPos="128" YPos="192" Width="64" Height="64" />

  <Image Name="CharHeadFrame4_DFS201902_Target" XPos="192" YPos="192" Width="64" Height="64" />

</Imageset>
