<?xml version="1.0" ?>
<Imageset Name="CircularTaskTool75" Imagefile="Icons/CircularTaskTool75.jpg" NativeHorzRes="1024" NativeVertRes="769" AutoScaled="true">
	<Image Name="CircularTaskTool75_1" XPos="0" YPos="0" Width="64" Height="64" />
	<Image Name="CircularTaskTool75_2" XPos="64" YPos="0" Width="64" Height="64" />
	<Image Name="CircularTaskTool75_3" XPos="128" YPos="0" Width="64" Height="64" />
	<Image Name="CircularTaskTool75_4" XPos="192" YPos="0" Width="64" Height="64" />
	<Image Name="CircularTaskTool75_5" XPos="0" YPos="64" Width="64" Height="64" />
	<Image Name="CircularTaskTool75_6" XPos="64" YPos="64" Width="64" Height="64" />
	<Image Name="CircularTaskTool75_7" XPos="128" YPos="64" Width="64" Height="64" />
	<Image Name="CircularTaskTool75_8" XPos="192" YPos="64" Width="64" Height="64" />
	<Image Name="CircularTaskTool75_9" XPos="0" YPos="128" Width="64" Height="64" />
	<Image Name="CircularTaskTool75_10" XPos="64" YPos="128" Width="64" Height="64" />
	<Image Name="CircularTaskTool75_11" XPos="128" YPos="128" Width="64" Height="64" />
	<Image Name="CircularTaskTool75_12" XPos="192" YPos="128" Width="64" Height="64" />
	<Image Name="CircularTaskTool75_13" XPos="0" YPos="192" Width="64" Height="64" />
	<Image Name="CircularTaskTool75_14" XPos="64" YPos="192" Width="64" Height="64" />
	<Image Name="CircularTaskTool75_15" XPos="128" YPos="192" Width="64" Height="64" />
	<Image Name="CircularTaskTool75_16" XPos="192" YPos="192" Width="64" Height="64" />
</Imageset>
