<?xml version="1.0" ?>
<Imageset Name="BaoJianUI5" Imagefile="Common/tga_BaoJianUI5.dds" NativeHorzRes="1024" NativeVertRes="768" AutoScaled="false">
  <Image Name="BaoYuMu_Disabled" XPos="0" YPos="0" Width="57" Height="57" />

  <Image Name="BaoYuShui_Normal" XPos="60" YPos="0" Width="57" Height="57" />
  <Image Name="BaoYuShui_Hover" XPos="120" YPos="0" Width="57" Height="57" />
  <Image Name="BaoYuShui_Pushed" XPos="180" YPos="0" Width="57" Height="57" />
  <Image Name="BaoYuShui_Disabled" XPos="0" YPos="60" Width="57" Height="57" />

  <Image Name="BaoYuHuo_Normal" XPos="60" YPos="60" Width="57" Height="57" />
  <Image Name="BaoYuHuo_Hover" XPos="120" YPos="60" Width="57" Height="57" />
  <Image Name="BaoYuHuo_Pushed" XPos="180" YPos="60" Width="57" Height="57" />
  <Image Name="BaoYuHuo_Disabled" XPos="0" YPos="120" Width="57" Height="57" />

  <Image Name="BaoYuTu_Normal" XPos="60" YPos="120" Width="57" Height="57" />
  <Image Name="BaoYuTu_Hover" XPos="120" YPos="120" Width="57" Height="57" />
  <Image Name="BaoYuTu_Pushed" XPos="180" YPos="120" Width="57" Height="57" />
  <Image Name="BaoYuTu_Disabled" XPos="0" YPos="180" Width="57" Height="57" />
  
</Imageset>