<?xml version="1.0" ?>
<Imageset Name="Createshowname" Imagefile="Common/Createshowname.tga" NativeHorzRes="1024" NativeVertRes="768"
          AutoScaled="true">
    <Image Name="Cs_Song_Normal" XPos="0" YPos="0" Width="170" Height="170"/>
    <Image Name="Cs_Song_Hover" XPos="170" YPos="0" Width="170" Height="170"/>
    <Image Name="Cs_Song_Pushed" XPos="340" YPos="0" Width="170" Height="170"/>

    <Image Name="Cs_Liao_Normal" XPos="0" YPos="170" Width="170" Height="170"/>
    <Image Name="Cs_Liao_Hover" XPos="170" YPos="170" Width="170" Height="170"/>
    <Image Name="Cs_Liao_Pushed" XPos="340" YPos="170" Width="170" Height="170"/>

    <Image Name="Cs_Yan_Normal" XPos="0" YPos="340" Width="170" Height="170"/>
    <Image Name="Cs_Yan_Hover" XPos="170" YPos="340" Width="170" Height="170"/>
    <Image Name="Cs_Yan_Pushed" XPos="340" YPos="340" Width="170" Height="170"/>

</Imageset>
