<?xml version="1.0" ?>
	<Imageset Name="NpcVisible" Imagefile="Common/tga_NpcVisible.dds" NativeHorzRes="1024" NativeVertRes="768" AutoScaled="false">
		<Image Name="NpcVisible_1" XPos="0" YPos="0" Width="25" Height="25" />
		<Image Name="NpcVisible_2" XPos="25" YPos="0" Width="25" Height="25" />
		<Image Name="NpcVisible_3" XPos="50" YPos="0" Width="25" Height="25" />
		<Image Name="NpcVisible_4" XPos="75" YPos="0" Width="25" Height="25" />
		<Image Name="NpcVisible_5" XPos="100" YPos="0" Width="25" Height="25" />
		<Image Name="NpcVisible_6" XPos="125" YPos="0" Width="25" Height="25" />
		<Image Name="NpcVisible_7" XPos="150" YPos="0" Width="25" Height="25" />
		<Image Name="NpcVisible_8" XPos="175" YPos="0" Width="25" Height="25" />
		<Image Name="NpcVisible_9" XPos="200" YPos="0" Width="25" Height="25" />
		<Image Name="NpcVisible_10" XPos="225" YPos="0" Width="25" Height="25" />
		<Image Name="NpcVisible_11" XPos="0" YPos="25" Width="25" Height="25" />
		<Image Name="NpcVisible_12" XPos="25" YPos="25" Width="25" Height="25" />
  </Imageset>