<?xml version="1.0" ?>
<Imageset Name="TServerUI7" Imagefile="Common/tga_TServerUI7.dds" NativeHorzRes="1024" NativeVertRes="768" AutoScaled="false">
  <Image Name="TServer_Tab" XPos="0" YPos="0" Width="280" Height="243" />

  <Image Name="TServerUI7_XS_Normal" XPos="430" YPos="0" Width="63" Height="63" />
  <Image Name="TServerUI7_XS_Hover" XPos="430" YPos="90" Width="63" Height="63" />
  <Image Name="TServerUI7_XS_Pushed" XPos="430" YPos="153" Width="63" Height="63" />
  <Image Name="TServerUI7_XS_Disabled" XPos="430" YPos="216" Width="63" Height="63" />

  <Image Name="TServer_Zhanche" XPos="430" YPos="71" Width="15" Height="15" />

  <Image Name="Zhuque_Red_Normal" XPos="282" YPos="0" Width="48" Height="76" />
  <Image Name="Zhuque_Red_Hover" XPos="330" YPos="0" Width="48" Height="76" />
  <Image Name="Zhuque_Red_Pushed" XPos="378" YPos="0" Width="48" Height="76" />

  <Image Name="Zhuque_Yellow_Normal" XPos="282" YPos="76" Width="48" Height="76" />
  <Image Name="Zhuque_Yellow_Hover" XPos="330" YPos="76" Width="48" Height="76" />
  <Image Name="Zhuque_Yellow_Pushed" XPos="378" YPos="76" Width="48" Height="76" />

  <Image Name="Zhuque_Blue_Normal" XPos="282" YPos="152" Width="48" Height="76" />
  <Image Name="Zhuque_Blue_Hover" XPos="330" YPos="152" Width="48" Height="76" />
  <Image Name="Zhuque_Blue_Pushed" XPos="378" YPos="152" Width="48" Height="76" />

  <Image Name="YUANBAO_Normal" XPos="0" YPos="250" Width="138" Height="32" />
  <Image Name="YUANBAO_Hover" XPos="0" YPos="282" Width="138" Height="32" />
  <Image Name="YUANBAO_Pushed" XPos="0" YPos="314" Width="138" Height="32" />
  <Image Name="YUANBAO_Disable" XPos="0" YPos="346" Width="138" Height="32" />
  
  <Image Name="JINBI_Normal" XPos="0" YPos="378" Width="138" Height="32" />
  <Image Name="JINBI_Hover" XPos="0" YPos="410" Width="138" Height="32" />
  <Image Name="JINBI_Pushed" XPos="0" YPos="442" Width="138" Height="32" />
  <Image Name="JINBI_Disable" XPos="0" YPos="474" Width="138" Height="32" />

  
</Imageset>