<?xml version="1.0" ?>
<Imageset Name="TServerUI4" Imagefile="Common/tga_TServerUI4.dds" NativeHorzRes="1024" NativeVertRes="768" AutoScaled="false">
  <Image Name="Qiaofeng_5" XPos="0" YPos="0" Width="280" Height="243" />
  <Image Name="Qiaofeng_6" XPos="0" YPos="250" Width="280" Height="243" />

  <Image Name="Earth_Normal" XPos="285" YPos="0" Width="170" Height="30" />
  <Image Name="Earth_Hover" XPos="285" YPos="30" Width="170" Height="30" />
  <Image Name="Earth_Pushed" XPos="285" YPos="60" Width="170" Height="30" />

  <Image Name="Sky_Normal" XPos="285" YPos="90" Width="170" Height="30" />
  <Image Name="Sky_Hover" XPos="285" YPos="120" Width="170" Height="30" />
  <Image Name="Sky_Pushed" XPos="285" YPos="150" Width="170" Height="30" />

  <Image Name="Xuan_Normal" XPos="285" YPos="180" Width="170" Height="30" />
  <Image Name="Xuan_Hover" XPos="285" YPos="210" Width="170" Height="30" />
  <Image Name="Xuan_Pushed" XPos="285" YPos="240" Width="170" Height="30" />
</Imageset>